padiff/__init__.py
padiff/auto_diff.py
padiff/file_loader.py
padiff/utils.py
padiff/weights.py
padiff/configs/api_mapping.json
padiff/configs/assign_weight.yaml
padiff/special_init/__init__.py
padiff/special_init/init_BatchNorm2D.py
padiff/special_init/init_LSTM.py
padiff/special_init/init_MultiHeadAttention.py
padiff/special_init/special_init_pool.py
padiff/trainer/Checker.py
padiff/trainer/OptimizerHelper.py
padiff/trainer/Runner.py
padiff/trainer/Trainer.py
padiff/trainer/__init__.py
padiff/trainer/trainer_utils/__init__.py
padiff/trainer/trainer_utils/actions.py
padiff/trainer/trainer_utils/hooks.py
padiff/trainer/trainer_utils/module_struct.py
padiff/trainer/trainer_utils/report.py
padiff-0.2.0.dist-info/METADATA
padiff-0.2.0.dist-info/WHEEL
padiff-0.2.0.dist-info/top_level.txt
padiff-0.2.0.dist-info/RECORD
