Metadata-Version: 2.1
Name: padiff
Version: 0.2.0
Summary: A tools to automatically diff precision between Paddle and Pytorch Model.
Home-page: https://github.com/PaddlePaddle/PaDiff
Author: PaddlePaddle Author
Author-email: 
License: Apache 2.0
Keywords: padiff automatically diff precision between paddle and pytorch model
Classifier: Programming Language :: Python :: 3
Classifier: Programming Language :: Python :: 3.7
Classifier: Programming Language :: Python :: 3.8
Classifier: Programming Language :: Python :: 3.9
Classifier: License :: OSI Approved :: Apache Software License
Classifier: Operating System :: OS Independent
Requires-Python: >=3.7
Requires-Dist: numpy
